{
  "RSpec": {
    "coverage": {
      "/home/nikita/Documents/RailsProj/hotel_booker/app/models/admin.rb": {
        "lines": [
          null,
          null,
          1,
          null,
          null,
          1,
          null,
          null
        ],
        "branches": {
        }
      },
      "/home/nikita/Documents/RailsProj/hotel_booker/app/models/application_record.rb": {
        "lines": [
          null,
          null,
          1,
          1,
          null
        ],
        "branches": {
        }
      },
      "/home/nikita/Documents/RailsProj/hotel_booker/app/helpers/admins_helper.rb": {
        "lines": [
          null,
          null,
          1,
          null
        ],
        "branches": {
        }
      },
      "/home/nikita/Documents/RailsProj/hotel_booker/app/helpers/application_helper.rb": {
        "lines": [
          null,
          null,
          1,
          null
        ],
        "branches": {
        }
      },
      "/home/nikita/Documents/RailsProj/hotel_booker/app/helpers/bookings_helper.rb": {
        "lines": [
          null,
          null,
          1,
          null
        ],
        "branches": {
        }
      },
      "/home/nikita/Documents/RailsProj/hotel_booker/app/helpers/home_helper.rb": {
        "lines": [
          null,
          null,
          1,
          null
        ],
        "branches": {
        }
      },
      "/home/nikita/Documents/RailsProj/hotel_booker/app/helpers/reviews_helper.rb": {
        "lines": [
          null,
          null,
          1,
          null
        ],
        "branches": {
        }
      },
      "/home/nikita/Documents/RailsProj/hotel_booker/app/helpers/rooms_helper.rb": {
        "lines": [
          null,
          null,
          1,
          null
        ],
        "branches": {
        }
      },
      "/home/nikita/Documents/RailsProj/hotel_booker/app/jobs/report_generator_job.rb": {
        "lines": [
          null,
          null,
          1,
          1,
          null,
          1,
          0,
          0,
          0,
          null,
          null,
          null
        ],
        "branches": {
          "[:if, 0, 9, 6, 9, 57]": {
            "[:then, 1, 9, 24, 9, 38]": 0,
            "[:else, 2, 9, 41, 9, 57]": 0
          }
        }
      },
      "/home/nikita/Documents/RailsProj/hotel_booker/app/jobs/application_job.rb": {
        "lines": [
          null,
          null,
          1,
          null,
          null,
          null,
          null,
          null,
          null
        ],
        "branches": {
        }
      },
      "/home/nikita/Documents/RailsProj/hotel_booker/app/models/booking.rb": {
        "lines": [
          null,
          null,
          1,
          null,
          1,
          1,
          1,
          1,
          1,
          1,
          1,
          null,
          1,
          0,
          null,
          null,
          1,
          0,
          0,
          null,
          null,
          null,
          1,
          0,
          0,
          0,
          0,
          0,
          0,
          0,
          null,
          null,
          0,
          0,
          null,
          null,
          1,
          1,
          null,
          null
        ],
        "branches": {
        }
      },
      "/home/nikita/Documents/RailsProj/hotel_booker/app/models/review.rb": {
        "lines": [
          null,
          null,
          1,
          1,
          1,
          1,
          1,
          null,
          1,
          1,
          null,
          null,
          1,
          1,
          null,
          null
        ],
        "branches": {
        }
      },
      "/home/nikita/Documents/RailsProj/hotel_booker/app/models/room.rb": {
        "lines": [
          null,
          null,
          1,
          1,
          1,
          1,
          1,
          1,
          1,
          null
        ],
        "branches": {
        }
      }
    },
    "timestamp": 1632678220
  }
}
